atlas_rucio_policy_package/__init__.py
atlas_rucio_policy_package/archive_tape_metadata.py
atlas_rucio_policy_package/non_deterministic_pfn.py
atlas_rucio_policy_package/permission.py
atlas_rucio_policy_package/pfn2lfn.py
atlas_rucio_policy_package/schema.py
atlas_rucio_policy_package/scope.py
atlas_rucio_policy_package-0.8.0.dist-info/licenses/LICENSE
atlas_rucio_policy_package-0.8.0.dist-info/METADATA
atlas_rucio_policy_package-0.8.0.dist-info/WHEEL
atlas_rucio_policy_package-0.8.0.dist-info/top_level.txt
atlas_rucio_policy_package-0.8.0.dist-info/RECORD
