Metadata-Version: 2.4
Name: atlas_rucio_policy_package
Version: 0.8.0
Summary: Rucio policy package for the ATLAS experiment
Author-email: ATLAS ADC DDM <atlas-adc-ddm@cern.ch>
License:                                  Apache License
Classifier: Programming Language :: Python :: 3
Classifier: Operating System :: OS Independent
Requires-Python: >=3.9
License-File: LICENSE
Provides-Extra: dev
Requires-Dist: rucio>=35.5.0; extra == "dev"
Dynamic: license-file
